pypelyne/__init__.py
pypelyne/exceptions.py
pypelyne/drive/__init__.py
pypelyne/drive/csv.py
pypelyne/drive/excel.py
pypelyne/drive/flatfile.py
pypelyne/drive/snow.py
pypelyne/drive/sqlserver.py
pypelyne/transform/__init__.py
pypelyne/transform/addcol.py
pypelyne/transform/cutfile.py
pypelyne/transform/filter.py
pypelyne/transform/func.py
pypelyne/transform/parsejson.py
pypelyne/transform/remove_empty_rows.py
pypelyne/transform/removecol.py
pypelyne/transform/renamecol.py
pypelyne/transform/splitrow.py
pypelyne/transform/substr.py
pypelyne/transform/trimrow.py
pypelyne-0.0.1.dist-info/LICENSE
pypelyne-0.0.1.dist-info/METADATA
pypelyne-0.0.1.dist-info/WHEEL
pypelyne-0.0.1.dist-info/top_level.txt
pypelyne-0.0.1.dist-info/RECORD
