Metadata-Version: 2.1
Name: pypelyne
Version: 0.0.1
Summary: Tooling for data flow, transformations and general ETL tasks.
Home-page: https://github.com/samuelcorradi/storagy
Author: Samuel Corradi
Author-email: samuelcorradi@gmail.com
Classifier: Programming Language :: Python :: 3
Classifier: License :: OSI Approved :: Apache Software License
Classifier: Operating System :: OS Independent
Classifier: Topic :: Database
Requires-Python: >=3.7.8
License-File: LICENSE
